sabcalculatorpy.py
sabcalculatorpy-0.0.6.dist-info/LICENSE.txt
sabcalculatorpy-0.0.6.dist-info/METADATA
sabcalculatorpy-0.0.6.dist-info/WHEEL
sabcalculatorpy-0.0.6.dist-info/top_level.txt
sabcalculatorpy-0.0.6.dist-info/RECORD
