Metadata-Version: 2.1
Name: sabcalculatorpy
Version: 0.0.6
Summary: helps to solve/assist small calculations and conversion 
Author: Sabarishkanna
Classifier: Programming Language :: Python :: 3
Classifier: License :: OSI Approved :: MIT License
Classifier: Operating System :: OS Independent
Requires-Python: >=3.7
License-File: LICENSE.txt
Requires-Dist: numpy
